marketplace_hub_api/__init__.py
marketplace_hub_api/client.py
marketplace_hub_api-0.3.dist-info/METADATA
marketplace_hub_api-0.3.dist-info/WHEEL
marketplace_hub_api-0.3.dist-info/top_level.txt
marketplace_hub_api-0.3.dist-info/RECORD
