Metadata-Version: 2.1
Name: marketplace-hub-api
Version: 0.3
Summary: Find, Connect and Manage APIs
Home-page: https://github.com/Zyla-Labs/pypi-api-hub
Author: Marketplace-Hub-API
Author-email: hello@zylalabs.com
Keywords: Api Hub,APIs,Find, Connect and Manage APIs,APIs Management,APIs Connection,APIs Integration,APIs Automation,APIs Development
